Metadata-Version: 1.1
Name: np
Version: 0.1.4
Summary: np = numpy++: numpy with added convenience functionality
Home-page: https://github.com/k7hoven/np
Author: Koos Zevenhoven
Author-email: koos.zevenhoven@aalto.fi
License: BSD
Platform: UNKNOWN
Classifier: Development Status :: 4 - Beta
Classifier: Natural Language :: English
Classifier: Operating System :: OS Independent
Classifier: Programming Language :: Python :: 2.7
Classifier: Programming Language :: Python :: 3
